arcana/testing/__init__.py
arcana/testing/_version.py
arcana/testing/data.py
arcana/testing/tasks.py
arcana_testing-0.1.3.dist-info/METADATA
arcana_testing-0.1.3.dist-info/WHEEL
arcana_testing-0.1.3.dist-info/licenses/LICENSE
arcana_testing-0.1.3.dist-info/RECORD
