Metadata-Version: 2.1
Name: arcana-testing
Version: 0.1.3
Summary: Dummy classes for testing the Arcana framework
Project-URL: repository, https://github.com/ArcanaFramework/arcana-testing
Author-email: "Thomas G. Close" <tom.g.close@gmail.com>
Maintainer-email: "Thomas G. Close" <tom.g.close@gmail.com>
License: Creative Commons Attribution 4.0 International Public License
License-File: LICENSE
Keywords: arcana,data repository,dataflow
Classifier: Development Status :: 2 - Pre-Alpha
Classifier: Environment :: Console
Classifier: Intended Audience :: Science/Research
Classifier: License :: OSI Approved :: Apache Software License
Classifier: Operating System :: MacOS :: MacOS X
Classifier: Operating System :: Microsoft :: Windows
Classifier: Operating System :: POSIX :: Linux
Classifier: Programming Language :: Python :: 3.7
Classifier: Programming Language :: Python :: 3.8
Classifier: Programming Language :: Python :: 3.9
Classifier: Programming Language :: Python :: 3.10
Classifier: Programming Language :: Python :: 3.11
Classifier: Topic :: Scientific/Engineering
Requires-Python: >=3.7
Requires-Dist: arcana
Requires-Dist: pydra>=0.20.0
Provides-Extra: dev
Requires-Dist: black; extra == 'dev'
Requires-Dist: codespell; extra == 'dev'
Requires-Dist: flake8; extra == 'dev'
Requires-Dist: flake8-pyproject; extra == 'dev'
Requires-Dist: pre-commit; extra == 'dev'
Provides-Extra: doc
Requires-Dist: docutils>=0.10; extra == 'doc'
Requires-Dist: furo>=2022.2.14.1; extra == 'doc'
Requires-Dist: mock>1.0; extra == 'doc'
Requires-Dist: numpydoc>=0.6.0; extra == 'doc'
Requires-Dist: packaging; extra == 'doc'
Requires-Dist: sphinx-argparse>=0.2.0; extra == 'doc'
Requires-Dist: sphinx-click>=3.1; extra == 'doc'
Requires-Dist: sphinx>=2.1.2; extra == 'doc'
Provides-Extra: test
Requires-Dist: codecov; extra == 'test'
Requires-Dist: pytest-cov; extra == 'test'
Requires-Dist: pytest-env; extra == 'test'
Requires-Dist: pytest>=4.4.0; extra == 'test'
